[
  {
    "ZIP": "52240",
    "ACTIVE": 1,
    "ROA": -0.06,
    "DEPDOM": 3865233,
    "DATEUPDT": "06/24/2019",
    "ROE": -0.47,
    "STNAME": "Iowa",
    "ASSET": 4757120,
    "OFFICES": 58,
    "NETINC": -669,
    "DEP": 3865233,
    "NAME": "MidWestOne Bank",
    "CBSA": "Iowa City, IA",
    "CITY": "Iowa City",
    "OFFDOM": 58,
    "CERT": "14843",
    "STALP": "IA",
    "COUNTY": "Johnson",
    "ID": "14843"
  },
  {
    "ZIP": "51445",
    "ACTIVE": 1,
    "ROA": 1.55,
    "DEPDOM": 1430130,
    "DATEUPDT": "11/20/2019",
    "ROE": 13.95,
    "STNAME": "Iowa",
    "ASSET": 1768302,
    "OFFICES": 37,
    "NETINC": 6804,
    "DEP": 1430130,
    "NAME": "United Bank of Iowa",
    "CITY": "Ida Grove",
    "OFFDOM": 37,
    "CERT": "958",
    "STALP": "IA",
    "COUNTY": "Ida",
    "ID": "958"
  },
  {
    "ZIP": "52002",
    "ACTIVE": 1,
    "ROA": 1.25,
    "DEPDOM": 1165482,
    "DATEUPDT": "12/27/2019",
    "ROE": 10.06,
    "STNAME": "Iowa",
    "ASSET": 1360691,
    "OFFICES": 33,
    "NETINC": 4287,
    "DEP": 1165482,
    "NAME": "Fidelity Bank & Trust",
    "CBSA": "Dubuque, IA",
    "CITY": "Dubuque",
    "OFFDOM": 33,
    "CERT": "14382",
    "STALP": "IA",
    "COUNTY": "Dubuque",
    "ID": "14382"
  },
  {
    "ZIP": "50309",
    "ACTIVE": 1,
    "ROA": 1.03,
    "DEPDOM": 3938856,
    "DATEUPDT": "07/11/2019",
    "ROE": 10.5,
    "STNAME": "Iowa",
    "ASSET": 4994580,
    "OFFICES": 27,
    "NETINC": 12852,
    "DEP": 3938856,
    "NAME": "Bankers Trust Company",
    "CBSA": "Des Moines-West Des Moines, IA",
    "CITY": "Des Moines",
    "OFFDOM": 27,
    "CERT": "953",
    "STALP": "IA",
    "COUNTY": "Polk",
    "ID": "953"
  },
  {
    "ZIP": "50588",
    "ACTIVE": 1,
    "ROA": 0.68,
    "DEPDOM": 1138774,
    "DATEUPDT": "03/10/2020",
    "ROE": 6.77,
    "STNAME": "Iowa",
    "ASSET": 1282692,
    "OFFICES": 26,
    "NETINC": 1871,
    "DEP": 1138774,
    "NAME": "Central Bank",
    "CBSA": "Storm Lake, IA",
    "CITY": "Storm Lake",
    "OFFDOM": 26,
    "CERT": "15555",
    "STALP": "IA",
    "COUNTY": "Buena Vista",
    "ID": "15555"
  },
  {
    "ZIP": "50266",
    "ACTIVE": 1,
    "ROA": 0.68,
    "DEPDOM": 1253794,
    "DATEUPDT": "12/27/2019",
    "ROE": 7.12,
    "STNAME": "Iowa",
    "ASSET": 1481359,
    "OFFICES": 25,
    "NETINC": 2451,
    "DEP": 1253794,
    "NAME": "Bank Iowa",
    "CBSA": "Des Moines-West Des Moines, IA",
    "CITY": "West Des Moines",
    "OFFDOM": 26,
    "CERT": "14521",
    "STALP": "IA",
    "COUNTY": "Dallas",
    "ID": "14521"
  },
  {
    "ZIP": "52235",
    "ACTIVE": 1,
    "ROA": 0.86,
    "DEPDOM": 2734416,
    "DATEUPDT": "02/07/2012",
    "ROE": 6.67,
    "STNAME": "Iowa",
    "ASSET": 3364758,
    "OFFICES": 20,
    "NETINC": 7128,
    "DEP": 2734416,
    "NAME": "Hills Bank and Trust Company",
    "CBSA": "Iowa City, IA",
    "CITY": "Hills",
    "OFFDOM": 20,
    "CERT": "14650",
    "STALP": "IA",
    "COUNTY": "Johnson",
    "ID": "14650"
  },
  {
    "ZIP": "51301",
    "ACTIVE": 1,
    "ROA": 0.71,
    "DEPDOM": 1449987,
    "DATEUPDT": "06/05/2015",
    "ROE": 7.29,
    "STNAME": "Iowa",
    "ASSET": 1741890,
    "OFFICES": 20,
    "NETINC": 3039,
    "DEP": 1449987,
    "NAME": "Northwest Bank",
    "CBSA": "Spencer, IA",
    "CITY": "Spencer",
    "OFFDOM": 20,
    "CERT": "32647",
    "STALP": "IA",
    "COUNTY": "Clay",
    "ID": "32647"
  },
  {
    "ZIP": "51401",
    "ACTIVE": 1,
    "ROA": 0.92,
    "DEPDOM": 930878,
    "DATEUPDT": "08/29/2019",
    "ROE": 8.31,
    "STNAME": "Iowa",
    "ASSET": 1099471,
    "OFFICES": 17,
    "NETINC": 2509,
    "DEP": 930878,
    "NAME": "Availa Bank",
    "CBSA": "Carroll, IA",
    "CITY": "Carroll",
    "OFFDOM": 17,
    "CERT": "11771",
    "STALP": "IA",
    "COUNTY": "Carroll",
    "ID": "11771"
  },
  {
    "ZIP": "50669",
    "ACTIVE": 1,
    "ROA": 0.85,
    "DEPDOM": 1102666,
    "DATEUPDT": "03/18/2020",
    "ROE": 7.57,
    "STNAME": "Iowa",
    "ASSET": 1355684,
    "OFFICES": 17,
    "NETINC": 2908,
    "DEP": 1102666,
    "NAME": "Lincoln Savings Bank",
    "CBSA": "Waterloo-Cedar Falls, IA",
    "CITY": "Reinbeck",
    "OFFDOM": 17,
    "CERT": "14207",
    "STALP": "IA",
    "COUNTY": "Grundy",
    "ID": "14207"
  }
]
